apiverve_opensourcelicenses/__init__.py
apiverve_opensourcelicenses/apiClient.py
apiverve_opensourcelicenses/exceptions.py
apiverve_opensourcelicenses/setup.py
apiverve_opensourcelicenses/setup_dep.py
apiverve_opensourcelicenses/tests/__init__.py
apiverve_opensourcelicenses/tests/test_api.py
apiverve_opensourcelicenses-1.1.5.dist-info/LICENSE
apiverve_opensourcelicenses-1.1.5.dist-info/METADATA
apiverve_opensourcelicenses-1.1.5.dist-info/WHEEL
apiverve_opensourcelicenses-1.1.5.dist-info/top_level.txt
apiverve_opensourcelicenses-1.1.5.dist-info/RECORD
